setup.cfg
setup.py
blot/__init__.py
blot/summarize.py
blot/utils.py
blot.egg-info/PKG-INFO
blot.egg-info/SOURCES.txt
blot.egg-info/dependency_links.txt
blot.egg-info/requires.txt
blot.egg-info/top_level.txt
blot/assets/__init__.py
blot/assets/autosummary.py
blot/assets/base.py
blot/assets/categories.py
blot/assets/categorytags.py
blot/assets/humanizer.py
blot/assets/metadata.py
blot/assets/series.py
blot/assets/seriestags.py
blot/assets/slugifier.py
blot/assets/tags.py
blot/assets/titler.py
blot/loaders/__init__.py
blot/loaders/basicloader.py
blot/readers/__init__.py
blot/readers/markdownreader.py
blot/readers/staticreader.py
blot/writers/__init__.py
blot/writers/indexwriter.py
blot/writers/listwriter.py
blot/writers/paginatedwriter.py
blot/writers/staticwriter.py