Metadata-Version: 1.0
Name: blot
Version: 0.0.11
Summary: An unassuming static site-generator for Python
Home-page: http://github.com/dustinlacewell/blot
Author: Dustin Lacewell
Author-email: dlacewell@gmail.com
License: UNKNOWN
Keywords: site-generator
Platform: UNKNOWN
